pyitau/__init__.py
pyitau/main.py
pyitau/pages.py
pyitau-1.3.1.dist-info/LICENSE
pyitau-1.3.1.dist-info/METADATA
pyitau-1.3.1.dist-info/WHEEL
pyitau-1.3.1.dist-info/top_level.txt
pyitau-1.3.1.dist-info/RECORD
