Metadata-Version: 2.1
Name: pyitau
Version: 1.3.1
Summary: Scraper to download data from Itaú Internet Banking
Home-page: https://github.com/lucasrcezimbra/pyitau
Author: Lucas Rangel Cezimbra
Author-email: lucas.cezimbra@gmail.com
License: LGPLv2
Keywords: pyitau,itau,api,client,requests,banking,bank,finance,accounting
Classifier: Development Status :: 5 - Production/Stable
Classifier: Intended Audience :: Developers
Classifier: License :: OSI Approved :: GNU Lesser General Public License v2 (LGPLv2)
Classifier: Programming Language :: Python :: 3
Classifier: Programming Language :: Python :: 3.6
Classifier: Programming Language :: Python :: 3.7
Classifier: Programming Language :: Python :: 3 :: Only
License-File: LICENSE
Requires-Dist: beautifulsoup4
Requires-Dist: cached-property
Requires-Dist: requests
